prompttools/__init__.py
prompttools/common.py
prompttools/sentry.py
prompttools/version.py
prompttools/benchmarks/__init__.py
prompttools/benchmarks/benchmark.py
prompttools/experiment/__init__.py
prompttools/experiment/experiments/__init__.py
prompttools/experiment/experiments/_utils.py
prompttools/experiment/experiments/anthropic_completion_experiment.py
prompttools/experiment/experiments/chromadb_experiment.py
prompttools/experiment/experiments/error.py
prompttools/experiment/experiments/experiment.py
prompttools/experiment/experiments/google_gemini_chat_experiment.py
prompttools/experiment/experiments/google_palm_experiment.py
prompttools/experiment/experiments/google_vertex_chat_experiment.py
prompttools/experiment/experiments/huggingface_endpoint_experiment.py
prompttools/experiment/experiments/huggingface_hub_experiment.py
prompttools/experiment/experiments/lancedb_experiment.py
prompttools/experiment/experiments/langchain_experiment.py
prompttools/experiment/experiments/llama_cpp_experiment.py
prompttools/experiment/experiments/mindsdb_experiment.py
prompttools/experiment/experiments/mistral_experiment.py
prompttools/experiment/experiments/openai_chat_experiment.py
prompttools/experiment/experiments/openai_completion_experiment.py
prompttools/experiment/experiments/pinecone_experiment.py
prompttools/experiment/experiments/qdrant_experiment.py
prompttools/experiment/experiments/replicate_experiment.py
prompttools/experiment/experiments/stablediffusion_experiment.py
prompttools/experiment/experiments/weaviate_experiment.py
prompttools/experiment/widgets/__init__.py
prompttools/experiment/widgets/comparison.py
prompttools/experiment/widgets/feedback.py
prompttools/experiment/widgets/utility.py
prompttools/harness/__init__.py
prompttools/harness/chat_history_harness.py
prompttools/harness/chat_model_comparison_harness.py
prompttools/harness/chat_prompt_template_harness.py
prompttools/harness/document_retrieval_harness.py
prompttools-0.0.46.dist-info/LICENSE
prompttools-0.0.46.dist-info/METADATA
prompttools-0.0.46.dist-info/WHEEL
prompttools-0.0.46.dist-info/top_level.txt
prompttools-0.0.46.dist-info/RECORD
