Metadata-Version: 2.1
Name: prompttools
Version: 0.0.46
Summary: Tools for LLM prompt testing and experimentation
Home-page: https://github.com/hegelai/prompttools
Author: Hegel AI
Author-email: Hegel AI <team@hegel-ai.com>
License: Proprietary
Project-URL: Homepage, https://github.com/hegelai/prompttools
Project-URL: Bug Tracker, https://github.com/hegelai/prompttools
Classifier: Programming Language :: Python :: 3
Classifier: License :: OSI Approved :: Apache Software License
Classifier: Operating System :: OS Independent
Requires-Python: >=3.10
License-File: LICENSE
Requires-Dist: openai
Requires-Dist: tenacity
Requires-Dist: tabulate
Requires-Dist: pandas
Requires-Dist: jinja2
Requires-Dist: jupyterlab
Requires-Dist: ipywidgets
Requires-Dist: pylint
Requires-Dist: sentry-sdk>=1.23.0
